astrolabium/__init__.py
astrolabium/catalogues/__init__.py
astrolabium/catalogues/catalogue_base.py
astrolabium/catalogues/catalogue_filters.py
astrolabium/catalogues/crossref.py
astrolabium/catalogues/hipparcos.py
astrolabium/catalogues/iau.py
astrolabium/catalogues/orb6.py
astrolabium/catalogues/wds.py
astrolabium/config.py
astrolabium/converters/__init__.py
astrolabium/converters/iau.py
astrolabium/creator/__init__.py
astrolabium/creator/catalogue_creator.py
astrolabium/creator/galaxy.py
astrolabium/creator/star.py
astrolabium/creator/system.py
astrolabium/creator/wds_analyser.py
astrolabium/fileIO.py
astrolabium/parsers/__init__.py
astrolabium/parsers/data/__init__.py
astrolabium/parsers/data/entry_base.py
astrolabium/parsers/data/hip_entry.py
astrolabium/parsers/data/orb6_entry.py
astrolabium/parsers/data/text.py
astrolabium/parsers/data/wds_entry.py
astrolabium/parsers/data/wikidata_star.py
astrolabium/parsers/gliese_parser.py
astrolabium/parsers/hip_parser.py
astrolabium/parsers/orb6_parser.py
astrolabium/parsers/parser_base.py
astrolabium/parsers/wds_parser.py
astrolabium/queries/__init__.py
astrolabium/queries/gaia.py
astrolabium/queries/simbad.py
astrolabium/queries/wiki_entities.py
astrolabium/queries/wikidata.py
astrolabium/table.py
astrolabium-0.1.1.dist-info/LICENSE
astrolabium-0.1.1.dist-info/METADATA
astrolabium-0.1.1.dist-info/WHEEL
astrolabium-0.1.1.dist-info/RECORD
